format_duration/__init__.py
format_duration/enums.py
format_duration/functions.py
format_duration/utils.py
format_duration-0.0.5.dist-info/LICENSE
format_duration-0.0.5.dist-info/METADATA
format_duration-0.0.5.dist-info/WHEEL
format_duration-0.0.5.dist-info/top_level.txt
format_duration-0.0.5.dist-info/RECORD
