Metadata-Version: 2.1
Name: format_duration
Version: 0.0.5
Summary: Python package to format duration
Author-email: Mufaddal Patanwala <mufaddal1125@gmail.com>
License: Copyright (c) 2018 The Python Packaging Authority
Project-URL: Homepage, https://github.com/Mufaddal1125/format_duration
Project-URL: Bug Tracker, https://github.com/Mufaddal1125/format_duration/issues
Classifier: Programming Language :: Python :: 3
Classifier: License :: OSI Approved :: MIT License
Classifier: Operating System :: OS Independent
Requires-Python: >=3.7
License-File: LICENSE
